pylowasm/__init__.py
pylowasm/pyregister.py
pylowasm/bin/32/libpyregister.a
pylowasm/bin/32/libpyregister.so
pylowasm/bin/32/pyregister.dll
pylowasm/bin/64/libpyregister.a
pylowasm/bin/64/libpyregister.so
pylowasm/bin/64/pyregister.dll
pylowasm-0.0.3.dist-info/METADATA
pylowasm-0.0.3.dist-info/WHEEL
pylowasm-0.0.3.dist-info/top_level.txt
pylowasm-0.0.3.dist-info/RECORD
